chook/__init__.py
chook/__main__.py
chook/file_handler.py
chook/input_handler.py
chook/run_chook.py
chook/spin_utils.py
chook/wrappers.py
chook/planters/__init__.py
chook/planters/fcl_generator.py
chook/planters/klocal_generator.py
chook/planters/regular_xorsat.py
chook/planters/tile_planting.py
chook/planters/wishart_planting.py
chook-0.2.0.data/data/params.in
chook-0.2.0.dist-info/LICENSE
chook-0.2.0.dist-info/METADATA
chook-0.2.0.dist-info/WHEEL
chook-0.2.0.dist-info/entry_points.txt
chook-0.2.0.dist-info/top_level.txt
chook-0.2.0.dist-info/RECORD
