Metadata-Version: 2.1
Name: chook
Version: 0.2.0
Summary: A comprehensive suite for generating binary optimization problems with planted solutions
Home-page: UNKNOWN
Author: Dilina Perera, Inimfon Akpabio
Author-email: dilinanp@gmail.com
License: UNKNOWN
Platform: UNKNOWN
Requires-Python: >=3.4
Requires-Dist: scipy
Requires-Dist: more-itertools
